odoo10_addon_base_ubl_payment-10.0.1.0.0-py2.7-nspkg.pth
odoo/addons/base_ubl_payment/README.rst
odoo/addons/base_ubl_payment/__init__.py
odoo/addons/base_ubl_payment/__manifest__.py
odoo/addons/base_ubl_payment/models/__init__.py
odoo/addons/base_ubl_payment/models/ubl.py
odoo10_addon_base_ubl_payment-10.0.1.0.0.dist-info/DESCRIPTION.rst
odoo10_addon_base_ubl_payment-10.0.1.0.0.dist-info/METADATA
odoo10_addon_base_ubl_payment-10.0.1.0.0.dist-info/RECORD
odoo10_addon_base_ubl_payment-10.0.1.0.0.dist-info/WHEEL
odoo10_addon_base_ubl_payment-10.0.1.0.0.dist-info/metadata.json
odoo10_addon_base_ubl_payment-10.0.1.0.0.dist-info/namespace_packages.txt
odoo10_addon_base_ubl_payment-10.0.1.0.0.dist-info/top_level.txt
